cameratransform/__init__.py
cameratransform/camera.py
cameratransform/gps.py
cameratransform/gui_tools/__init__.py
cameratransform/gui_tools/calibrate/QExtendedGraphicsView.py
cameratransform/gui_tools/calibrate/__init__.py
cameratransform/gui_tools/calibrate/calibrate.py
cameratransform/gui_tools/calibrate/gui_calibrate.py
cameratransform/gui_tools/demonstrator/QtShortCuts.py
cameratransform/gui_tools/demonstrator/__init__.py
cameratransform/gui_tools/demonstrator/demo_includes.py
cameratransform/gui_tools/demonstrator/demo_matplotlib.py
cameratransform/gui_tools/demonstrator/demo_qt.py
cameratransform/lens_distortion.py
cameratransform/parameter_set.py
cameratransform/projection.py
cameratransform/ray.py
cameratransform/scene.py
cameratransform/spatial.py
cameratransform/statistic.py
cameratransform/utils.py
cameratransform-1.2.1.dist-info/LICENSE.txt
cameratransform-1.2.1.dist-info/METADATA
cameratransform-1.2.1.dist-info/WHEEL
cameratransform-1.2.1.dist-info/RECORD
